wg_easy_api_wrapper/__init__.py
wg_easy_api_wrapper/client.py
wg_easy_api_wrapper/errors.py
wg_easy_api_wrapper/server.py
wg_easy_api_wrapper-1.0.8.dist-info/LICENSE
wg_easy_api_wrapper-1.0.8.dist-info/METADATA
wg_easy_api_wrapper-1.0.8.dist-info/WHEEL
wg_easy_api_wrapper-1.0.8.dist-info/top_level.txt
wg_easy_api_wrapper-1.0.8.dist-info/RECORD
