Metadata-Version: 2.1
Name: wg-easy-api-wrapper
Version: 1.0.8
Summary: Wrapper for wg-easy API
Home-page: https://github.com/Shandeika/wg-easy-api-wrapper
Author: MrShandy
Author-email: mrshandy@shandy-dev.ru
License: GPL-3.0
Classifier: Programming Language :: Python :: 3.10
Classifier: License :: OSI Approved :: GNU General Public License v3 (GPLv3)
Classifier: Operating System :: Microsoft :: Windows
Classifier: Operating System :: POSIX :: Linux
Classifier: Topic :: Software Development :: Libraries :: Python Modules
License-File: LICENSE
Requires-Dist: aiohttp ~=3.9.0
